chatty_shell/__init__.py
chatty_shell/backend/__init__.py
chatty_shell/backend/agent.py
chatty_shell/backend/exceptions.py
chatty_shell/backend/messages.py
chatty_shell/backend/model.py
chatty_shell/backend/prompts.py
chatty_shell/backend/tools.py
chatty_shell/frontend/__init__.py
chatty_shell/frontend/ascii.py
chatty_shell/frontend/view.py
chatty_shell/main.py
chatty_shell/presenter/__init__.py
chatty_shell/presenter/presenter.py
chatty_shell-0.2.2.dist-info/LICENSE
chatty_shell-0.2.2.dist-info/METADATA
chatty_shell-0.2.2.dist-info/WHEEL
chatty_shell-0.2.2.dist-info/entry_points.txt
chatty_shell-0.2.2.dist-info/RECORD
