Metadata-Version: 2.1
Name: chatty-shell
Version: 0.2.2
Summary: 
Author: Artur Dernst
Author-email: artur@dernst.me
Requires-Python: >=3.10,<4.0
Classifier: Programming Language :: Python :: 3
Classifier: Programming Language :: Python :: 3.10
Classifier: Programming Language :: Python :: 3.11
Classifier: Programming Language :: Python :: 3.12
Requires-Dist: langchain (>=0.3.26,<0.4.0)
Requires-Dist: langchain-community (>=0.3.27,<0.4.0)
Requires-Dist: langchain-openai (>=0.3.27,<0.4.0)
Requires-Dist: langgraph (>=0.5.1,<0.6.0)
Requires-Dist: pyperclip (>=1.9.0,<2.0.0)
